skyport/__init__.py
skyport/cli.py
skyport-0.1.0.dist-info/LICENSE
skyport-0.1.0.dist-info/METADATA
skyport-0.1.0.dist-info/WHEEL
skyport-0.1.0.dist-info/entry_points.txt
skyport-0.1.0.dist-info/RECORD
