Metadata-Version: 2.1
Name: skyport
Version: 0.1.0
Summary: Skyport is a cli for obtaining information from astronomical objects.
Author: Henrique Sebastião
Author-email: contato@henriquesebastiao.com
Requires-Python: >=3.11,<4.0
Classifier: Development Status :: 5 - Production/Stable
Classifier: Environment :: Console
Classifier: Intended Audience :: Education
Classifier: Intended Audience :: Science/Research
Classifier: License :: Other/Proprietary License
Classifier: Natural Language :: English
Classifier: Programming Language :: Python :: 3
Classifier: Programming Language :: Python :: 3.11
Classifier: Programming Language :: Python :: 3.12
Classifier: Topic :: Education
Classifier: Topic :: Office/Business :: News/Diary
Classifier: Topic :: Scientific/Engineering :: Astronomy
Classifier: Topic :: Utilities
Requires-Dist: requests (>=2.31.0,<3.0.0)
Requires-Dist: typer[all] (>=0.9.0,<0.10.0)
Project-URL: Bug Tracker, https://github.com/henriquesebastiao/skyport/issues
Project-URL: Documentation, https://skyport.henriquesebastiao.com
Project-URL: Homepage, https://skyport.henriquesebastiao.com
Project-URL: Repository, https://github.com/henriquesebastiao/skyport
